[
  {
    "method": "get",
    "endpoint": "/application-base/{id}/profile",
    "endUrl": "/application-base/6000/profile",
    "apiResp": {
      "profileId": 2222,
      "summary": "Summary of Key Skills\r\n•   Valued team player with\t•   Effectively bilingual in English\r\nexperience in working in\tand Mandarin, spoken and\r\ncohesive teams.\twritten\r\n•   Peer support lead in School of\t•   Critical thinking\r\nHospitality club.\t•   Interpersonal skills\r\n•   An effective team leader with\r\nvisions who manages teams in\r\nplanning multiple events.\r\n•   Service oriented",
      "genderId": 1,
      "firstName": "ba5b8c48e5819339999fea1cd4128c80",
      "middleName": null,
      "lastName": "",
      "preferName": null,
      "birthDate": null,
      "marriageId": null,
      "email": "19025013@myrp.edu.sg",
      "addressId": "3378",
      "nationalityId": null,
      "totalExp": "5.8728507283",
      "managementExp": null,
      "courtCharge": null,
      "bankruptcy": null,
      "crime": null,
      "linkedin": "linkedin.com/in/leanne-leong-75a72518a",
      "facebook": null,
      "salary": null,
      "currencyId": null,
      "entryUserId": null,
      "createDate": "2021-05-10T00:00:00.000Z",
      "updateDate": "2021-05-18T00:00:00.000Z",
      "profileIndex": "x2819x0x58fe43a4-2bef-4245-b9ac-e83c947c9763",
      "teamId": "13265",
      "ethnicityId": 4,
      "globalTalent": false,
      "twitter": null,
      "militaryTitle": null,
      "militaryRank": null,
      "agreeStoreApplication": null,
      "agreeTalentPool": null,
      "agreeRecommendations": null,
      "gdprConsentDate": null,
      "youtubeLink": null,
      "linkedinIdentifier": null,
      "expectedSalary": null,
      "placeOfBirth": null,
      "overallScore": null,
      "scoreBreakdown": null,
      "lang": null,
      "linkedProfileId": null,
      "sourceProfileId": null,
      "industryId": null,
      "personalEmail": null,
      "isDisable": null,
      "residentStatus": "singapore",
      "suspended": false,
      "tier": null,
      "iv": "be08b2cae43e047305e0b6653127ab14",
      "selected": null,
      "batch": "AY21 Sem 2",
      "scholar": null,
      "ringFenced": false,
      "permanentAddressId": null
    }
  }
]